MANIFEST.in
README.md
requirements.txt
setup.py
django_mp_exchange.egg-info/PKG-INFO
django_mp_exchange.egg-info/SOURCES.txt
django_mp_exchange.egg-info/dependency_links.txt
django_mp_exchange.egg-info/requires.txt
django_mp_exchange.egg-info/top_level.txt
exchange/__init__.py
exchange/actions.py
exchange/admin.py
exchange/constants.py
exchange/context_processors.py
exchange/forms.py
exchange/managers.py
exchange/models.py
exchange/querysets.py
exchange/tasks.py
exchange/urls.py
exchange/utils.py
exchange/views.py
exchange/locale/ru/LC_MESSAGES/django.mo
exchange/locale/ru/LC_MESSAGES/django.po
exchange/locale/uk/LC_MESSAGES/django.mo
exchange/locale/uk/LC_MESSAGES/django.po
exchange/migrations/0001_initial.py
exchange/migrations/__init__.py
exchange/templates/exchange/update_prices.html
exchange/templatetags/__init__.py
exchange/templatetags/exchange.py