Metadata-Version: 2.1
Name: django-mp-exchange
Version: 1.0.2
Summary: Django exchange app
Home-page: https://github.com/pmaigutyak/mp-exchange
Author: Paul Maigutyak
Author-email: pmaigutyak@gmail.com
License: MIT
Download-URL: https://github.com/pmaigutyak/mp-exchange/archive/1.0.2.tar.gz
Platform: UNKNOWN
